{
    "keep": {
        "days": false,
        "amount": 1000
    },
    "auditLog": "log/.audit.json",
    "files": [
        {
            "date": 1523518473918,
            "name": "log\\server_2018-04-12.log",
            "hash": "0a4959e7552d47df05a7d161ec579192"
        },
        {
            "date": 1523518473928,
            "name": "log\\exception_2018-04-12.log",
            "hash": "8d9541a1a96fbbc4d87a860af3189759"
        },
        {
            "date": 1523518559900,
            "name": "log\\server_2018-04-12.log",
            "hash": "2fd2af9ea1867271fc4dd8de7fa539e7"
        },
        {
            "date": 1523518559903,
            "name": "log\\exception_2018-04-12.log",
            "hash": "7d058f9e3df00391325cd0ce2e9343a6"
        },
        {
            "date": 1523518612223,
            "name": "log\\server_2018-04-12.log",
            "hash": "92c87153fc21f798b3265088141fe60f"
        },
        {
            "date": 1523518612226,
            "name": "log\\exception_2018-04-12.log",
            "hash": "5cfebc3e2b46b10cdcf16abac4917561"
        },
        {
            "date": 1523518772556,
            "name": "log\\server_2018-04-12.log",
            "hash": "3587f64708b2aa4530e699aa494c2171"
        },
        {
            "date": 1523518772559,
            "name": "log\\exception_2018-04-12.log",
            "hash": "170da764a9220588982178b0c44b14ac"
        },
        {
            "date": 1523548859095,
            "name": "log\\server_2018-04-13.log",
            "hash": "59fef4a0a0a4b114a4e4ce66c3482c41"
        },
        {
            "date": 1523548859102,
            "name": "log\\exception_2018-04-13.log",
            "hash": "2fae2381b05034e072221345377f3a9d"
        },
        {
            "date": 1523548907963,
            "name": "log\\server_2018-04-13.log",
            "hash": "7659433bbcf967949e2c44bc8ab77476"
        },
        {
            "date": 1523548907969,
            "name": "log\\exception_2018-04-13.log",
            "hash": "2e4fbc937230960666d9645eddcf0770"
        },
        {
            "date": 1523548945093,
            "name": "log\\server_2018-04-13.log",
            "hash": "5f95c619748e6d838f20abed4fdf3fa2"
        },
        {
            "date": 1523548945100,
            "name": "log\\exception_2018-04-13.log",
            "hash": "52feb78358060f62e24190c93a1f1b1b"
        },
        {
            "date": 1523548969836,
            "name": "log\\server_2018-04-13.log",
            "hash": "1fb6f6ff8372432b4fc47fdbd48ee9ac"
        },
        {
            "date": 1523548969842,
            "name": "log\\exception_2018-04-13.log",
            "hash": "3fe04f7e7e6d7b39346a1e7da55c5a9a"
        },
        {
            "date": 1523549096865,
            "name": "log\\server_2018-04-13.log",
            "hash": "0d7e21e276018ba50368e63e4d9a5e76"
        },
        {
            "date": 1523549096872,
            "name": "log\\exception_2018-04-13.log",
            "hash": "7cb9ae77e26cc10d36488f04ca302acd"
        },
        {
            "date": 1523549117142,
            "name": "log\\server_2018-04-13.log",
            "hash": "7b2fbc6d6ec206403f4a5bce2a35d6a9"
        },
        {
            "date": 1523549117149,
            "name": "log\\exception_2018-04-13.log",
            "hash": "02d680e9a2d7937805bcae8bfc8c99ce"
        },
        {
            "date": 1523549142367,
            "name": "log\\server_2018-04-13.log",
            "hash": "5143c0f46fc7f608e4e53701d29c8e38"
        },
        {
            "date": 1523549142373,
            "name": "log\\exception_2018-04-13.log",
            "hash": "909979e1b47570a25385519a7a8904b8"
        },
        {
            "date": 1523549147511,
            "name": "log\\server_2018-04-13.log",
            "hash": "e0cbe7706b65d349d477bd95d7c1f0b5"
        },
        {
            "date": 1523549147518,
            "name": "log\\exception_2018-04-13.log",
            "hash": "3aa4e9f0d42c14e00a8a68906fe67dec"
        },
        {
            "date": 1523549162256,
            "name": "log\\server_2018-04-13.log",
            "hash": "994e6fbf8de58ae23d61d80d1252aabc"
        },
        {
            "date": 1523549162262,
            "name": "log\\exception_2018-04-13.log",
            "hash": "9457167b44a5e51f5e4e560d85634258"
        },
        {
            "date": 1523549289273,
            "name": "log\\server_2018-04-13.log",
            "hash": "89cf3b345f14172ec01afab6885721cf"
        },
        {
            "date": 1523549289279,
            "name": "log\\exception_2018-04-13.log",
            "hash": "a2315134d2ffac5877760eb170de0686"
        },
        {
            "date": 1523549352609,
            "name": "log\\server_2018-04-13.log",
            "hash": "1cf6fcf6c57667b818c69465b6b82cb1"
        },
        {
            "date": 1523549352617,
            "name": "log\\exception_2018-04-13.log",
            "hash": "3d49ab921beeac091cfb561a32f4b110"
        },
        {
            "date": 1523549370789,
            "name": "log\\server_2018-04-13.log",
            "hash": "61ebfc93220fdda41b0e82ffe477fbe0"
        },
        {
            "date": 1523549370796,
            "name": "log\\exception_2018-04-13.log",
            "hash": "88bbd43da018ab9838c08971f3094b02"
        },
        {
            "date": 1523549730634,
            "name": "log\\server_2018-04-13.log",
            "hash": "f8aa25bfa5ad0c9eab60812077c72c7e"
        },
        {
            "date": 1523549730641,
            "name": "log\\exception_2018-04-13.log",
            "hash": "96c7dc5845f00a2e1a9a085b47c4097f"
        },
        {
            "date": 1523549784431,
            "name": "log\\server_2018-04-13.log",
            "hash": "5aacfbc8e1226cabd01eb30679b1af25"
        },
        {
            "date": 1523549784437,
            "name": "log\\exception_2018-04-13.log",
            "hash": "94d7c0e859e3e40d4b9dc2809c346b0c"
        },
        {
            "date": 1523549843080,
            "name": "log\\server_2018-04-13.log",
            "hash": "2579e4559070803c2d9b80565d6c1fbb"
        },
        {
            "date": 1523549843086,
            "name": "log\\exception_2018-04-13.log",
            "hash": "00ea1e891691c175482fcbb856f1780c"
        },
        {
            "date": 1523549872238,
            "name": "log\\server_2018-04-13.log",
            "hash": "e093a01eed247dd7ddfb03ec118e188a"
        },
        {
            "date": 1523549872245,
            "name": "log\\exception_2018-04-13.log",
            "hash": "c7ce5252e06f7e0337791eb08c2e275d"
        },
        {
            "date": 1523549891855,
            "name": "log\\server_2018-04-13.log",
            "hash": "822d3f5ebfb1e6e5e6a542c2c8fd69fd"
        },
        {
            "date": 1523549891862,
            "name": "log\\exception_2018-04-13.log",
            "hash": "bfc3054a2b613cf38011bf77d71d4c06"
        },
        {
            "date": 1523549920100,
            "name": "log\\server_2018-04-13.log",
            "hash": "5950bd3ac42c196bc5b04147a58f80d5"
        },
        {
            "date": 1523549920106,
            "name": "log\\exception_2018-04-13.log",
            "hash": "eda10bedf9b21da56b03ee6fb26ba96c"
        },
        {
            "date": 1523549937814,
            "name": "log\\server_2018-04-13.log",
            "hash": "cf1e1081b667cf49cefa60f22e3d203c"
        },
        {
            "date": 1523549937821,
            "name": "log\\exception_2018-04-13.log",
            "hash": "10ea804ff7df825242bce72972ebf0b9"
        },
        {
            "date": 1523549961900,
            "name": "log\\server_2018-04-13.log",
            "hash": "08864c87439778b9769ebe28bc0a3344"
        },
        {
            "date": 1523549961906,
            "name": "log\\exception_2018-04-13.log",
            "hash": "18974233ea7f0356e7687271eac39497"
        },
        {
            "date": 1523550030898,
            "name": "log\\server_2018-04-13.log",
            "hash": "0a167d64725d774cfe1e5f7d19880625"
        },
        {
            "date": 1523550030937,
            "name": "log\\exception_2018-04-13.log",
            "hash": "2089e43b5b0a4da7524d2449bf6bd7c9"
        },
        {
            "date": 1523550064902,
            "name": "log\\server_2018-04-13.log",
            "hash": "6e96ee17416c18c13c59cb7ceb9d7e2f"
        },
        {
            "date": 1523550064909,
            "name": "log\\exception_2018-04-13.log",
            "hash": "93b9243232270fa11b4657055947cc09"
        },
        {
            "date": 1523550110946,
            "name": "log\\server_2018-04-13.log",
            "hash": "8fb117d266c1a1fe1d3aa94a1d0b75e6"
        },
        {
            "date": 1523550110953,
            "name": "log\\exception_2018-04-13.log",
            "hash": "076c12a55b7421e3077de7eeb6868b2d"
        },
        {
            "date": 1523550123219,
            "name": "log\\server_2018-04-13.log",
            "hash": "861a919620d271485ff292cd60adc8ce"
        },
        {
            "date": 1523550123227,
            "name": "log\\exception_2018-04-13.log",
            "hash": "8f94e2ea39d5c459ecbcf11122aa6320"
        },
        {
            "date": 1523550148957,
            "name": "log\\server_2018-04-13.log",
            "hash": "5557c2468f3dd8d014a1df0f1bb95626"
        },
        {
            "date": 1523550148969,
            "name": "log\\exception_2018-04-13.log",
            "hash": "143f744b081075dec155c81e809f8eff"
        },
        {
            "date": 1523550215089,
            "name": "log\\server_2018-04-13.log",
            "hash": "abfa6e50521f91819fee300e2cdc9784"
        },
        {
            "date": 1523550215097,
            "name": "log\\exception_2018-04-13.log",
            "hash": "2daab591d0de6f917cc9ab52128758ad"
        },
        {
            "date": 1523550445158,
            "name": "log\\server_2018-04-13.log",
            "hash": "fda5302382abae02ed991386fc23cb69"
        },
        {
            "date": 1523550445167,
            "name": "log\\exception_2018-04-13.log",
            "hash": "74cdc4a96ac0e76ba36cbed41fb318e2"
        },
        {
            "date": 1523550547942,
            "name": "log\\server_2018-04-13.log",
            "hash": "fcc44eddca9ab808efcada27c09c4cf3"
        },
        {
            "date": 1523550547950,
            "name": "log\\exception_2018-04-13.log",
            "hash": "d54b17beff4f52c9e01de425daad2d18"
        },
        {
            "date": 1523550579278,
            "name": "log\\server_2018-04-13.log",
            "hash": "6265e026a4a354f1df10dfe37b0866de"
        },
        {
            "date": 1523550579299,
            "name": "log\\exception_2018-04-13.log",
            "hash": "d42c1edde5cc1bc2e43bce735eeff7ee"
        },
        {
            "date": 1523550763099,
            "name": "log\\server_2018-04-13.log",
            "hash": "110561df4dc7b9a7549e1269768a2fa9"
        },
        {
            "date": 1523550763106,
            "name": "log\\exception_2018-04-13.log",
            "hash": "71d69020422f28c3d15f09b3b4abcefd"
        },
        {
            "date": 1523550813099,
            "name": "log\\server_2018-04-13.log",
            "hash": "a627cd0f4e420f2c86ecac83997729b6"
        },
        {
            "date": 1523550813107,
            "name": "log\\exception_2018-04-13.log",
            "hash": "bb81318049d62e8cff40cb39c6917c60"
        },
        {
            "date": 1523550849693,
            "name": "log\\server_2018-04-13.log",
            "hash": "b9d4013f0557f5315fc8a8da0dd2e6a4"
        },
        {
            "date": 1523550849701,
            "name": "log\\exception_2018-04-13.log",
            "hash": "80929f83c1fd8d324a64bec648404d3c"
        },
        {
            "date": 1523550889909,
            "name": "log\\server_2018-04-13.log",
            "hash": "e6784313bfe762d2ccf68c214cc1e873"
        },
        {
            "date": 1523550889919,
            "name": "log\\exception_2018-04-13.log",
            "hash": "e18d073a3d8d33316fdec697cecba45d"
        },
        {
            "date": 1523550970990,
            "name": "log\\server_2018-04-13.log",
            "hash": "6fc3ba8e00ac29bba7ca57f4e50687f2"
        },
        {
            "date": 1523550970996,
            "name": "log\\exception_2018-04-13.log",
            "hash": "4bd8f20d071d6d3afeffd8aad1be8b3b"
        },
        {
            "date": 1523551136074,
            "name": "log\\server_2018-04-13.log",
            "hash": "a1703d32c5297737f547b7fa24280475"
        },
        {
            "date": 1523551136082,
            "name": "log\\exception_2018-04-13.log",
            "hash": "6f2a99431b595a8ae83ef65f13ade603"
        },
        {
            "date": 1523551214354,
            "name": "log\\server_2018-04-13.log",
            "hash": "fc543dee8bf453011691b137496a9839"
        },
        {
            "date": 1523551214362,
            "name": "log\\exception_2018-04-13.log",
            "hash": "481399e9fb3a63dbef961d71892c7f52"
        },
        {
            "date": 1523551240983,
            "name": "log\\server_2018-04-13.log",
            "hash": "932dbafd11c6d8c9465e3caf9881a7b2"
        },
        {
            "date": 1523551240990,
            "name": "log\\exception_2018-04-13.log",
            "hash": "344db66151603cf0f12a546cef9273b3"
        },
        {
            "date": 1523551404492,
            "name": "log\\server_2018-04-13.log",
            "hash": "13d1bb5a595db9f71f342f42b2b1bd3d"
        },
        {
            "date": 1523551404500,
            "name": "log\\exception_2018-04-13.log",
            "hash": "c04eea29dd9373c77c512da1a08de803"
        },
        {
            "date": 1523626649127,
            "name": "log\\server_2018-04-13.log",
            "hash": "9bc286757fc02bcf931462c31bf76823"
        },
        {
            "date": 1523626649134,
            "name": "log\\exception_2018-04-13.log",
            "hash": "584c8d29b3b836450cc2a4cd18042b40"
        }
    ]
}